MANIFEST.in
README.md
setup.cfg
setup.py
ilmulti/__init__.py
ilmulti/__version__.py
ilmulti.egg-info/PKG-INFO
ilmulti.egg-info/SOURCES.txt
ilmulti.egg-info/dependency_links.txt
ilmulti.egg-info/requires.txt
ilmulti.egg-info/top_level.txt
ilmulti/align/__init__.py
ilmulti/align/bleu_align.py
ilmulti/io/__init__.py
ilmulti/io/writer.py
ilmulti/segment/__init__.py
ilmulti/segment/base_segmenter.py
ilmulti/segment/pattern_segmenter.py
ilmulti/segment/simple_segmenter.py
ilmulti/segment/punkt_segmenter/__init__.py
ilmulti/segment/punkt_segmenter/punkt.py
ilmulti/segment/punkt_segmenter/punkt_segmenter.py
ilmulti/segment/punkt_segmenter/test.py
ilmulti/segment/punkt_segmenter/train.py
ilmulti/segment/punkt_segmenter/utils.py
ilmulti/segment/punkt_segmenter/models/bn.pib.news.pickle
ilmulti/segment/punkt_segmenter/models/en.pib.news.pickle
ilmulti/segment/punkt_segmenter/models/gu.pib.news.pickle
ilmulti/segment/punkt_segmenter/models/hi.pib.news.pickle
ilmulti/segment/punkt_segmenter/models/ml.pib.news.pickle
ilmulti/segment/punkt_segmenter/models/mr.pib.news.pickle
ilmulti/segment/punkt_segmenter/models/or.pib.news.pickle
ilmulti/segment/punkt_segmenter/models/pa.pib.news.pickle
ilmulti/segment/punkt_segmenter/models/ta.pib.news.pickle
ilmulti/segment/punkt_segmenter/models/te.pib.news.pickle
ilmulti/segment/punkt_segmenter/models/ur.pib.news.pickle
ilmulti/sentencepiece/__init__.py
ilmulti/sentencepiece/core.py
ilmulti/sentencepiece/models/__init__.py
ilmulti/sentencepiece/models/bn.4000.model
ilmulti/sentencepiece/models/bn.4000.vocab
ilmulti/sentencepiece/models/de.32000.model
ilmulti/sentencepiece/models/de.32000.vocab
ilmulti/sentencepiece/models/en.32000.model
ilmulti/sentencepiece/models/en.32000.vocab
ilmulti/sentencepiece/models/en.4000.model
ilmulti/sentencepiece/models/en.4000.vocab
ilmulti/sentencepiece/models/en.8000.model
ilmulti/sentencepiece/models/en.8000.vocab
ilmulti/sentencepiece/models/gu.4000.model
ilmulti/sentencepiece/models/gu.4000.vocab
ilmulti/sentencepiece/models/hi.32000.model
ilmulti/sentencepiece/models/hi.32000.vocab
ilmulti/sentencepiece/models/hi.4000.model
