Metadata-Version: 2.1
Name: ilmulti
Version: 0.0.1
Summary: Multilingual Text Tooling around Indian Languages
Home-page: https://github.com/jerinphilip/ilmulti
Author: Jerin Philip
Author-email: jerin.philip@research.iiit.ac.in
License: MIT
Platform: UNKNOWN
Classifier: License :: OSI Approved :: MIT License
Classifier: Programming Language :: Python
Classifier: Programming Language :: Python :: 3
Classifier: Programming Language :: Python :: 3.6
Classifier: Programming Language :: Python :: Implementation :: CPython
Classifier: Programming Language :: Python :: Implementation :: PyPy
Requires-Python: >=3.6.0
Provides-Extra: translation
